ovobdkit/__init__.py
ovobdkit/regex_check.py
ovobdkit/run_airflow.py
ovobdkit/run_omt.py
ovobdkit/run_try.py
ovobdkit/ovodevkit/__init__.py
ovobdkit/ovodevkit/base_task.py
ovobdkit/ovodevkit/hive2hive.py
ovobdkit/ovodevkit/mysql2hive.py
ovobdkit/ovodevkit/pgsql2hive.py
ovobdkit/ovodevkit/typing.py
ovobdkit/ovodevkit/utils.py
ovobdkit/ovotestkit/__init__.py
ovobdkit/ovotestkit/func.py
ovobdkit/ovotestkit/shell.py
ovobdkit/ovotestkit/source.py
ovobdkit/ovotestkit/unit.py
ovotestkit/__init__.py
ovotestkit/func.py
ovotestkit/unit.py
ovobdkit-1.0.10.dist-info/METADATA
ovobdkit-1.0.10.dist-info/WHEEL
ovobdkit-1.0.10.dist-info/top_level.txt
ovobdkit-1.0.10.dist-info/RECORD
